MANIFEST.in
README.md
setup.py
age_descriptor.egg-info/PKG-INFO
age_descriptor.egg-info/SOURCES.txt
age_descriptor.egg-info/dependency_links.txt
age_descriptor.egg-info/entry_points.txt
age_descriptor.egg-info/requires.txt
age_descriptor.egg-info/top_level.txt
person_descriptor/__init__.py
person_descriptor/descriptor.py
person_descriptor/runner.py