Metadata-Version: 2.1
Name: age-descriptor
Version: 0.1
Summary: Our first super useful library
Home-page: UNKNOWN
Author: SDA
Author-email: maila@mail.com
License: UNKNOWN
Platform: UNKNOWN
Requires-Python: >=3.8
